Discobot-0.1.0.dist-info/DESCRIPTION.rst
Discobot-0.1.0.dist-info/METADATA
Discobot-0.1.0.dist-info/RECORD
Discobot-0.1.0.dist-info/WHEEL
Discobot-0.1.0.dist-info/entry_points.txt
Discobot-0.1.0.dist-info/metadata.json
Discobot-0.1.0.dist-info/top_level.txt
discobot/__init__.py
discobot/__main__.py
discobot/bot.py
discobot/commands.py
discobot/constants.py
discobot/events.py
discobot/utils.py
