Metadata-Version: 2.0
Name: Discobot
Version: 0.1.0
Summary: A fully-featured music bot for Discord.
Home-page: https://github.com/chandler14362/disco
Author: Pythonology
Author-email: UNKNOWN
License: MIT
Platform: UNKNOWN
Classifier: Topic :: Communications :: Chat
Classifier: Topic :: Multimedia :: Sound/Audio :: Players
Classifier: Environment :: No Input/Output (Daemon)
Classifier: Development Status :: 2 - Pre-Alpha
Classifier: Intended Audience :: Developers
Classifier: Intended Audience :: End Users/Desktop
Classifier: Intended Audience :: Other Audience
Classifier: Intended Audience :: System Administrators
Classifier: License :: OSI Approved :: MIT License
Classifier: Natural Language :: English
Classifier: Operating System :: OS Independent
Classifier: Programming Language :: Python :: 3.5
Requires-Dist: PyYAML (==3.11)
Requires-Dist: redis (==2.10.5)
Requires-Dist: soundcloud (==0.5.0)
Requires-Dist: youtube-dl (==2016.4.13)
